py_firefox_driver_manager/Utilities.py
py_firefox_driver_manager/__init__.py
py_firefox_driver_manager-0.0.5.dist-info/METADATA
py_firefox_driver_manager-0.0.5.dist-info/WHEEL
py_firefox_driver_manager-0.0.5.dist-info/top_level.txt
py_firefox_driver_manager-0.0.5.dist-info/RECORD
