Metadata-Version: 2.1
Name: py-firefox-driver-manager
Version: 0.0.5
Summary: manage install firfox and Gecko Driver
Home-page: https://github.com/HamedMinaeizaeim/py-Gecko-FireFox-Driver-Manager
Author: Hamed
Author-email: hamed.minaei@gmail.com
Project-URL: Bug Tracker, https://github.com/HamedMinaeizaeim/py-Gecko-FireFox-Driver-Manager/issues
Classifier: Programming Language :: Python :: 3
Classifier: License :: OSI Approved :: MIT License
Classifier: Operating System :: OS Independent
Requires-Python: >=3.6
Requires-Dist: certifi (==2022.5.18.1)
Requires-Dist: charset-normalizer (==2.0.12)
Requires-Dist: distro (==1.7.0)
Requires-Dist: idna (==3.3)
Requires-Dist: mozdownload (==1.26.0)
Requires-Dist: mozfile (==2.1.0)
Requires-Dist: mozinfo (==1.2.2)
Requires-Dist: packaging (==21.3)
Requires-Dist: platinfo (==0.15.0)
Requires-Dist: progressbar2 (==4.0.0)
Requires-Dist: pyparsing (==3.0.9)
Requires-Dist: python-utils (==3.3.0)
Requires-Dist: redo (==2.0.3)
Requires-Dist: requests (==2.27.1)
Requires-Dist: six (==1.16.0)
Requires-Dist: style (==1.1.0)
Requires-Dist: treeherder-client (==5.0.0)
Requires-Dist: update (==0.0.1)
Requires-Dist: urllib3 (==1.26.9)
